omni_gumshoe/__init__.py
omni_gumshoe/apps.py
omni_gumshoe/signals.py
omni_gumshoe-0.1.1.dist-info/DESCRIPTION.rst
omni_gumshoe-0.1.1.dist-info/METADATA
omni_gumshoe-0.1.1.dist-info/RECORD
omni_gumshoe-0.1.1.dist-info/WHEEL
omni_gumshoe-0.1.1.dist-info/metadata.json
omni_gumshoe-0.1.1.dist-info/top_level.txt
