Metadata-Version: 2.0
Name: omni-gumshoe
Version: 0.1.1
Summary: Simple django signal for tracking superuser logins.
Home-page: https://github.com/omni-digital/omni-gumshoe
Author: Philip Gardner
Author-email: philip.gardner@omni-digital.co.uk
License: MIT
Keywords: omni_gumshoe,admin,logging
Platform: UNKNOWN
Classifier: Development Status :: 3 - Alpha
Classifier: Framework :: Django
Classifier: Framework :: Django :: 1.8
Classifier: Framework :: Django :: 1.9
Classifier: Framework :: Django :: 1.10
Classifier: Intended Audience :: Developers
Classifier: License :: OSI Approved :: BSD License
Classifier: Natural Language :: English
Classifier: Programming Language :: Python :: 2
Classifier: Programming Language :: Python :: 2.7
Classifier: Programming Language :: Python :: 3
Classifier: Programming Language :: Python :: 3.3
Classifier: Programming Language :: Python :: 3.4
Classifier: Programming Language :: Python :: 3.5
Classifier: Programming Language :: Python :: 3.6
